compute_core/__init__.py
compute_core/arrays.py
compute_core/fft.py
compute_core/linalg.py
scicomp_compute_core-0.1.6.dist-info/METADATA
scicomp_compute_core-0.1.6.dist-info/WHEEL
scicomp_compute_core-0.1.6.dist-info/RECORD
